<theme>
   <aspectRatio name="16:9">
      <view name="gamelist">
         <grid name="gamelist-grid">
            <itemSize>0.1981242 0.5708333</itemSize><!-- 5 across: 169 274 -->
         </grid>
      </view>
   </aspectRatio>
   <aspectRatio name="16:10">
      <view name="gamelist">
         <grid name="gamelist-grid">
            <itemSize>0.1979167 0.5125</itemSize><!-- 5 across: 152 246 -->
         </grid>
      </view>
   </aspectRatio>
   <aspectRatio name="3:2">
      <view name="gamelist">
         <grid name="gamelist-grid">
            <itemSize>0.1977778 0.48125</itemSize><!-- 5 across: 142.4 231 -->
         </grid>
      </view>
   </aspectRatio>
   <aspectRatio name="4:3,5:4">
      <view name="gamelist">
         <grid name="gamelist-grid">
            <itemSize>0.2476562 0.5354167</itemSize><!-- 4 across: 158.5 257 -->
         </grid>
      </view>
   </aspectRatio>
   <aspectRatio name="8:7">
      <view name="gamelist">
         <grid name="gamelist-grid">
            <itemSize>0.2472678 0.4583333</itemSize><!-- 4 across: 135.75 220 -->
         </grid>
      </view>
   </aspectRatio>
   <aspectRatio name="1:1">
      <view name="gamelist">
         <grid name="gamelist-grid">
            <itemSize>0.246875 0.4</itemSize><!-- 4 across: 118.5 192 -->
         </grid>
      </view>
   </aspectRatio>
   <aspectRatio name="19.5:9,20:9,21:9">
      <view name="gamelist">
         <grid name="gamelist-grid">
            <itemSize>0.140625 0.49375</itemSize><!-- 7 across: 146.25 237 -->
         </grid>
      </view>
   </aspectRatio>
   <aspectRatio name="32:9">
      <view name="gamelist">
         <grid name="gamelist-grid">
            <itemSize>0.0975967 0.5614583</itemSize><!-- 10 across: 166.5 269.5 -->
         </grid>
      </view>
   </aspectRatio>
   <aspectRatio name="5:3_vertical">
      <view name="gamelist">
         <grid name="gamelist-grid">
            <itemSize>0.328125 0.31875</itemSize><!-- 3 across: 94.5 153 -->
         </grid>
      </view>
   </aspectRatio>
</theme>